setup.py
zstat/__init__.py
zstat/main.py
zstat/settings.py
zstat.egg-info/PKG-INFO
zstat.egg-info/SOURCES.txt
zstat.egg-info/dependency_links.txt
zstat.egg-info/entry_points.txt
zstat.egg-info/requires.txt
zstat.egg-info/top_level.txt
zstat/modules/__init__.py
zstat/modules/mysql.py
zstat/modules/rabbitmq.py