Metadata-Version: 1.0
Name: zstat
Version: 0.0.6
Summary: A set of metrics to be sent to the Zabbix monitoring system
Home-page: https://github.com/sievetech/zstat
Author: Sievetech
Author-email: sievetech@sieve.com.br
License: 3-BSD
Platform: UNKNOWN
